MANIFEST.in
NetPyNE-UI
README.rst
setup.py
netpyne_ui/__init__.py
netpyne_ui/netpyne_geppetto.py
netpyne_ui/netpyne_model_interpreter.py
netpyne_ui/template.py
netpyne_ui/template2.py
netpyne_ui.egg-info/PKG-INFO
netpyne_ui.egg-info/SOURCES.txt
netpyne_ui.egg-info/dependency_links.txt
netpyne_ui.egg-info/requires.txt
netpyne_ui.egg-info/top_level.txt
netpyne_ui/geppetto/src/main/webapp/build/0.bundle.js
netpyne_ui/geppetto/src/main/webapp/build/0.bundle.js.map
netpyne_ui/geppetto/src/main/webapp/build/1.bundle.js
netpyne_ui/geppetto/src/main/webapp/build/1.bundle.js.map
netpyne_ui/geppetto/src/main/webapp/build/10.bundle.js
netpyne_ui/geppetto/src/main/webapp/build/10.bundle.js.map
netpyne_ui/geppetto/src/main/webapp/build/11.bundle.js
netpyne_ui/geppetto/src/main/webapp/build/11.bundle.js.map
netpyne_ui/geppetto/src/main/webapp/build/12.bundle.js
netpyne_ui/geppetto/src/main/webapp/build/12.bundle.js.map
netpyne_ui/geppetto/src/main/webapp/build/13.bundle.js
netpyne_ui/geppetto/src/main/webapp/build/13.bundle.js.map
netpyne_ui/geppetto/src/main/webapp/build/14.bundle.js
netpyne_ui/geppetto/src/main/webapp/build/14.bundle.js.map
netpyne_ui/geppetto/src/main/webapp/build/15.bundle.js
netpyne_ui/geppetto/src/main/webapp/build/15.bundle.js.map
netpyne_ui/geppetto/src/main/webapp/build/16.bundle.js
netpyne_ui/geppetto/src/main/webapp/build/16.bundle.js.map
netpyne_ui/geppetto/src/main/webapp/build/17.bundle.js
netpyne_ui/geppetto/src/main/webapp/build/17.bundle.js.map
netpyne_ui/geppetto/src/main/webapp/build/18.bundle.js
netpyne_ui/geppetto/src/main/webapp/build/18.bundle.js.map
netpyne_ui/geppetto/src/main/webapp/build/19.bundle.js
netpyne_ui/geppetto/src/main/webapp/build/19.bundle.js.map
netpyne_ui/geppetto/src/main/webapp/build/2.bundle.js
netpyne_ui/geppetto/src/main/webapp/build/2.bundle.js.map
netpyne_ui/geppetto/src/main/webapp/build/20.bundle.js
netpyne_ui/geppetto/src/main/webapp/build/20.bundle.js.map
netpyne_ui/geppetto/src/main/webapp/build/21.bundle.js
netpyne_ui/geppetto/src/main/webapp/build/21.bundle.js.map
netpyne_ui/geppetto/src/main/webapp/build/23.bundle.js
