Metadata-Version: 1.1
Name: netpyne-ui
Version: 0.5.1
Summary: NetPyNE User interface
Home-page: https://github.com/MetaCell/NetPyNE-UI
Author: MetaCell
Author-email: info@metacell.us
License: MIT
Platform: UNKNOWN
Classifier: Development Status :: 3 - Alpha
Classifier: Intended Audience :: Science/Research
Classifier: Topic :: Scientific/Engineering :: Visualization
Classifier: License :: OSI Approved :: MIT License
Classifier: Programming Language :: Python :: 3
Classifier: Programming Language :: Python :: 3.3
Classifier: Programming Language :: Python :: 3.4
Classifier: Programming Language :: Python :: 3.7
